Text-To-Speech-Easy3/__init__.py
python3easypyttsx3/__init__.py
tts/__init__.py
python3easypyttsx3-0.1.dist-info/METADATA
python3easypyttsx3-0.1.dist-info/WHEEL
python3easypyttsx3-0.1.dist-info/top_level.txt
python3easypyttsx3-0.1.dist-info/RECORD
